{"resource_uri": "https://www.courtlistener.com/api/rest/v4/clusters/9366854/", "id": 9366854, "absolute_url": "/opinion/9366854/andoe-v-biden/", "panel": [], "non_participating_judges": [], "docket_id": 66728240, "docket": "https://www.courtlistener.com/api/rest/v4/dockets/66728240/", "sub_opinions": ["https://www.courtlistener.com/api/rest/v4/opinions/9362330/"], "citations": [{"date_created": "2025-09-25T21:50:34.120042-07:00", "date_modified": "2025-09-25T21:50:34.139566-07:00", "volume": "140", "reporter": "S. Ct.", "page": "2730", "type": 1}, {"date_created": "2025-09-25T21:50:34.120042-07:00", "date_modified": "2025-09-25T21:50:34.139566-07:00", "volume": "206", "reporter": "L. Ed. 2d", "page": "861", "type": 1}], "date_created": "2023-01-12T23:07:31.496416-08:00", "date_modified": "2024-10-19T01:35:50.563688-07:00", "judges": "", "date_filed": "2020-04-27", "date_filed_is_approximate": false, "slug": "andoe-v-biden", "case_name_short": "Andoe", "case_name": "Andoe v. Biden", "case_name_full": "Johnny R. ANDOE v. Joe BIDEN", "scdb_id": "", "scdb_decision_direction": null, "scdb_votes_majority": null, "scdb_votes_minority": null, "source": "U", "procedural_history": "", "attorneys": "", "nature_of_suit": "", "posture": "", "syllabus": "", "headnotes": "", "summary": "", "disposition": "", "history": "", "other_dates": "", "cross_reference": "", "correction": "", "citation_count": 0, "precedential_status": "Published", "date_blocked": null, "blocked": false, "filepath_json_harvard": "law.free.cap.s-ct.140/2730.12627647.json", "filepath_pdf_harvard": null, "arguments": "", "headmatter": ""}